odoo/addons/helpdesk_email_reply_to_team/CHANGELOG.md
odoo/addons/helpdesk_email_reply_to_team/README.rst
odoo/addons/helpdesk_email_reply_to_team/__init__.py
odoo/addons/helpdesk_email_reply_to_team/__manifest__.py
odoo/addons/helpdesk_email_reply_to_team/models/__init__.py
odoo/addons/helpdesk_email_reply_to_team/models/helpdesk_ticket.py
odoo12_addon_helpdesk_email_reply_to_team-12.0.1.0.0.dist-info/METADATA
odoo12_addon_helpdesk_email_reply_to_team-12.0.1.0.0.dist-info/WHEEL
odoo12_addon_helpdesk_email_reply_to_team-12.0.1.0.0.dist-info/top_level.txt
odoo12_addon_helpdesk_email_reply_to_team-12.0.1.0.0.dist-info/RECORD
