Metadata-Version: 2.1
Name: odoo12-addon-helpdesk-email-reply-to-team
Version: 12.0.1.0.0
Summary: ODOO helpdesk_mgmt email reply to teams. When sending a message from a ticket now the recipient gets as reply-to "catchall@mycompany.com". Instead, the reply to should be "helpdesk-team-alias@mycompany.com". This was fixed for Odoo 14 and this module backports the fix to Odoo 12. (See https://github.com/OCA/helpdesk/pull/381)
Home-page: https://gitlab.com/somitcoop/erp-research/odoo-helpdesk
Author: Som It Cooperatiu SCCL, Som Connexió SCCL, Odoo Community Association (OCA)
Author-email: support@odoo-community.org
License: AGPL-3
Platform: UNKNOWN
Classifier: Programming Language :: Python
Classifier: Framework :: Odoo
Classifier: Framework :: Odoo :: 12.0
Classifier: License :: OSI Approved :: GNU Affero General Public License v3
Requires-Python: >=3.5
Requires-Dist: odoo12-addon-helpdesk-mgmt
Requires-Dist: odoo <12.1dev,>=12.0a
